bikewise/__init__.py
bikewise/bikewise.py
python_bikewise-0.1.0.dist-info/LICENSE
python_bikewise-0.1.0.dist-info/METADATA
python_bikewise-0.1.0.dist-info/WHEEL
python_bikewise-0.1.0.dist-info/top_level.txt
python_bikewise-0.1.0.dist-info/RECORD
