Metadata-Version: 2.1
Name: python-bikewise
Version: 0.1.0
Summary: A simple BikeWise API wrapper
Home-page: https://github.com/irahorecka/python-bikewise
Author: Ira Horecka
Author-email: ira89@icloud.com
License: MIT
Platform: UNKNOWN
Classifier: Development Status :: 3 - Alpha
Classifier: License :: OSI Approved :: MIT License
Classifier: Programming Language :: Python
Classifier: Programming Language :: Python :: 3.5
Classifier: Programming Language :: Python :: 3.6
Classifier: Programming Language :: Python :: 3.7
Classifier: Topic :: Software Development :: Libraries
Classifier: Topic :: Software Development :: Libraries :: Python Modules
Classifier: Intended Audience :: Developers
Requires-Python: >=3.5
Requires-Dist: requests
